{
"1": "RLRLRRLLRRLLRLRLRRLLRRLL",
"2": "LRLRLLRRLLRRLRLRLLRRLLRR",
"3": "RRLLRRLLRRLLRRLLRRLLRRLL",
"4": "LLRRLLRRLLRRLLRRLLRRLLRR",
"5": "RLRRLLRRLLRRLRLLRRLLRRLL",
"6": "RLLRLLRRLLRRLRRLRRLLRRLL",
"7": "RRLRLLRRLLRRLLRLRRLLRRLL",
"8": "RRRLRRLLRRLLRRRLRRLLRRLL",
"9": "LLLRLLRRLLRRLLLRLLRRLLRR",
"10": "RLLLRRLLRRLLRLLLRRLLRRLL",
"11": "LRRRLLRRLLRRLRRRLLRRLLRR",
"12": "RRRRLLRRLLRRLLLLRRLLRRLL",
"13": "RLRLRRLLRRLRLRLRRLLRRL",
"14": "LRLRLLRRLLRLRLRLLRRLLR",
"15": "RRLLRRLLRRLRRLLRRLLRRL",
"16": "LLRRLLRRLLRLLRRLLRRLLR",
"17": "RLRRLLRRLLRLRLLRRLLRRL",
"18": "RLLRLLRRLLRLRRLRRLLRRL",
"19": "RRLRLLRRLLRLLRLRRLLRRL",
"20": "RRRLRRLLRRLRRRLRRLLRRL",
"21": "LLLRLLRRLLRLLLRLLRRLLR",
"22": "RLLLRRLLRRLRLLLRRLLRRL",
"23": "LRRRLLRRLLRLRRRLLRRLLR",
"24": "RRRRLLRRLLRLLLLRRLLRRL"
}
